wandb_buddy/__init__.py
wandb_buddy/dataframe.py
wandb_buddy-0.1.0.dist-info/METADATA
wandb_buddy-0.1.0.dist-info/WHEEL
wandb_buddy-0.1.0.dist-info/RECORD
