Metadata-Version: 2.4
Name: wandb_buddy
Version: 0.1.0
Summary: Utilities for W&B experiment analysis
License: MIT
Requires-Python: >=3.8
Requires-Dist: pandas>=2.0.0
Requires-Dist: wandb>=0.22.0
Provides-Extra: dev
Requires-Dist: build; extra == 'dev'
Requires-Dist: twine; extra == 'dev'
